concept/__init__.py
concept/concept.py
concept/static/css/concept.css
concept/static/html/concept.html
concept/static/html/studio_hack.html
concept/static/js/concept.js
concept/static/js/oa_edit.js
concept/static/js/oa_server.js
concept_xblock-0.3.1.dist-info/LICENSE
concept_xblock-0.3.1.dist-info/METADATA
concept_xblock-0.3.1.dist-info/WHEEL
concept_xblock-0.3.1.dist-info/entry_points.txt
concept_xblock-0.3.1.dist-info/top_level.txt
concept_xblock-0.3.1.dist-info/RECORD
