Metadata-Version: 2.1
Name: concept-xblock
Version: 0.3.1
Summary: concept XBlock
License-File: LICENSE
Requires-Dist: XBlock
